barcodeQrSDK/__init__.py
barcodeQrSDK/scripts.py
barcode_qr_code_sdk-11.2.1000.dist-info/licenses/LICENSE
barcode_qr_code_sdk-11.2.1000.dist-info/METADATA
barcode_qr_code_sdk-11.2.1000.dist-info/WHEEL
barcode_qr_code_sdk-11.2.1000.dist-info/entry_points.txt
barcode_qr_code_sdk-11.2.1000.dist-info/top_level.txt
barcode_qr_code_sdk-11.2.1000.dist-info/RECORD
